general_classifier/__init__.py
general_classifier/gc.py
general_classifier-0.1.10.dist-info/METADATA
general_classifier-0.1.10.dist-info/WHEEL
general_classifier-0.1.10.dist-info/licenses/LICENSE
general_classifier-0.1.10.dist-info/RECORD
