Metadata-Version: 2.4
Name: general_classifier
Version: 0.1.10
Summary: This python package is designed to provide an adaptable framework for text classification. It can be used to manage and classify text across multiple topics using Large Language Models (LLMs).
Project-URL: Homepage, https://github.com/f-dennstaedt/general-classifier-py
Project-URL: Paper, https://www.medrxiv.org/content/10.1101/2024.12.03.24318390v1
Author-email: Fabio Dennstädt <fabiodennstaedt@gmx.de>
License-File: LICENSE
Classifier: License :: OSI Approved :: MIT License
Classifier: Operating System :: OS Independent
Classifier: Programming Language :: Python :: 3
Requires-Python: >=3.7
